samplomatic/__init__.py
samplomatic/_beta_warning.py
samplomatic/_version.py
samplomatic/aliases.py
samplomatic/constants.py
samplomatic/exceptions.py
samplomatic/optionals.py
samplomatic/partition.py
samplomatic/serializable.py
samplomatic/ssv.py
samplomatic/tensor_interface.py
samplomatic/annotations/__init__.py
samplomatic/annotations/change_basis.py
samplomatic/annotations/change_basis_mode.py
samplomatic/annotations/decomposition_mode.py
samplomatic/annotations/dressing_mode.py
samplomatic/annotations/inject_local_clifford.py
samplomatic/annotations/inject_noise.py
samplomatic/annotations/twirl.py
samplomatic/annotations/virtual_type.py
samplomatic/builders/__init__.py
samplomatic/builders/box_builder.py
samplomatic/builders/build.py
samplomatic/builders/builder.py
samplomatic/builders/get_builder.py
samplomatic/builders/param_iter.py
samplomatic/builders/passthrough_builder.py
samplomatic/builders/specs.py
samplomatic/builders/template_state.py
samplomatic/distributions/__init__.py
samplomatic/distributions/distribution.py
samplomatic/distributions/haar_u2.py
samplomatic/distributions/uniform_c1.py
samplomatic/distributions/uniform_pauli.py
samplomatic/graph_utils/__init__.py
samplomatic/graph_utils/find_unreachable_nodes.py
samplomatic/graph_utils/get_clusters.py
samplomatic/graph_utils/node_candidate.py
samplomatic/graph_utils/replace_edges_with_one_edge.py
samplomatic/graph_utils/replace_nodes_with_one_node.py
samplomatic/pre_samplex/__init__.py
samplomatic/pre_samplex/graph_data.py
samplomatic/pre_samplex/pre_samplex.py
samplomatic/pre_samplex/utils.py
samplomatic/samplex/__init__.py
samplomatic/samplex/interfaces.py
samplomatic/samplex/parameter_expression_table.py
samplomatic/samplex/samplex.py
samplomatic/samplex/nodes/__init__.py
samplomatic/samplex/nodes/change_basis_node.py
samplomatic/samplex/nodes/collect_template_values.py
samplomatic/samplex/nodes/collect_z2_to_output_node.py
samplomatic/samplex/nodes/collection_node.py
samplomatic-0.15.0.dist-info/licenses/LICENSE.txt
samplomatic-0.15.0.dist-info/METADATA
samplomatic-0.15.0.dist-info/WHEEL
samplomatic-0.15.0.dist-info/top_level.txt
samplomatic-0.15.0.dist-info/RECORD
