Metadata-Version: 2.4
Name: samplomatic
Version: 0.15.0
Summary: Serving all of your circuit sampling needs since 2025.
Author-email: Qiskit Development Team <qiskit@us.ibm.com>
License-Expression: Apache-2.0
Project-URL: Homepage, https://github.com/Qiskit/samplomatic
Project-URL: BugTracker, https://github.com/Qiskit/samplomatic/issues
Classifier: Development Status :: 3 - Alpha
Classifier: Intended Audience :: Developers
Classifier: Programming Language :: Python
Classifier: Programming Language :: Python :: 3
Classifier: Programming Language :: Python :: 3.11
Requires-Python: >=3.10
License-File: LICENSE.txt
Requires-Dist: qiskit>=2.2.0
Requires-Dist: numpy>=1.26
Requires-Dist: rustworkx>=0.16.0
Requires-Dist: pybase64>=1.4.0
Requires-Dist: orjson>=3.9.0
Provides-Extra: dev
Requires-Dist: pytest; extra == "dev"
Requires-Dist: pytest-benchmark; extra == "dev"
Requires-Dist: kaleido; extra == "dev"
Requires-Dist: ruff; extra == "dev"
Requires-Dist: pre-commit; extra == "dev"
Requires-Dist: towncrier; extra == "dev"
Requires-Dist: qiskit-aer; extra == "dev"
Requires-Dist: sphinx>=2.2; extra == "dev"
Requires-Dist: qiskit-sphinx-theme~=2.0.0; extra == "dev"
Requires-Dist: sphinx-automodapi; extra == "dev"
Requires-Dist: scipy-doctest>=2.0; extra == "dev"
Requires-Dist: sphinx-plotly-directive; extra == "dev"
Requires-Dist: myst-parser>=2.0; extra == "dev"
Requires-Dist: myst-nb; extra == "dev"
Provides-Extra: vis
Requires-Dist: nbformat>=4.2.0; extra == "vis"
Requires-Dist: plotly; extra == "vis"
Requires-Dist: matplotlib; extra == "vis"
Requires-Dist: pylatexenc; extra == "vis"
Dynamic: license-file
